xnatutils/__init__.py
xnatutils/_version.py
xnatutils/base.py
xnatutils/exceptions.py
xnatutils/get_.py
xnatutils/ls_.py
xnatutils/put_.py
xnatutils/rename_.py
xnatutils/varget_.py
xnatutils/varput_.py
xnatutils/version_.py
xnatutils-0.10.0.dist-info/METADATA
xnatutils-0.10.0.dist-info/WHEEL
xnatutils-0.10.0.dist-info/entry_points.txt
xnatutils-0.10.0.dist-info/licenses/AUTHORS
xnatutils-0.10.0.dist-info/licenses/LICENSE
xnatutils-0.10.0.dist-info/RECORD
