Metadata-Version: 2.4
Name: xnatutils
Version: 0.10.0
Summary: A collection of scripts for downloading/uploading and listing data from XNAT repositories.
Project-URL: repository, https://github.com/Australian-Imaging-Service/xnatutils
Author-email: "Thomas G. Close" <tom.g.close@gmail.com>
Maintainer-email: "Thomas G. Close" <tom.g.close@gmail.com>
License: 
License-File: AUTHORS
License-File: LICENSE
Keywords: DICOM,REST API,XNAT,uploader
Classifier: Development Status :: 4 - Beta
Classifier: Intended Audience :: Healthcare Industry
Classifier: Intended Audience :: Science/Research
Classifier: License :: OSI Approved :: Apache Software License
Classifier: Natural Language :: English
Classifier: Programming Language :: Python :: 3.4
Classifier: Programming Language :: Python :: 3.5
Classifier: Programming Language :: Python :: 3.6
Classifier: Programming Language :: Python :: 3.7
Classifier: Programming Language :: Python :: 3.8
Classifier: Topic :: Scientific/Engineering :: Bio-Informatics
Classifier: Topic :: Scientific/Engineering :: Medical Science Apps.
Requires-Python: >=3.8
Requires-Dist: future>=0.16
Requires-Dist: progressbar2>=3.16.0
Requires-Dist: xnat>=0.6
